maven/__init__.py
maven/get.py
maven/utils.py
maven/datasets/__init__.py
maven/datasets/test.py
maven/datasets/general_election/__init__.py
maven/datasets/general_election/base.py
maven/datasets/general_election/gb_2015_results.py
maven/datasets/general_election/uk_2010_results.py
maven/datasets/general_election/uk_2015_model.py
maven/datasets/general_election/uk_2015_results.py
maven/datasets/general_election/uk_2017_model.py
maven/datasets/general_election/uk_2017_results.py
maven/datasets/general_election/uk_2019_model.py
maven/datasets/general_election/uk_polls.py
maven-0.1.0.dist-info/AUTHORS.md
maven-0.1.0.dist-info/LICENSE
maven-0.1.0.dist-info/METADATA
maven-0.1.0.dist-info/WHEEL
maven-0.1.0.dist-info/top_level.txt
maven-0.1.0.dist-info/RECORD
