Metadata-Version: 2.1
Name: maven
Version: 0.1.0
Summary: Maven's goal is to reduce the time data scientists spend on data cleaning and preparation by providing easy access to open datasets in both raw and processed formats.
Home-page: https://github.com/john-sandall/maven
Author: John Sandall
Author-email: contact@coefficient.ai
License: Apache 2.0
Keywords: maven open data etl pipeline
Platform: UNKNOWN
Classifier: Development Status :: 2 - Pre-Alpha
Classifier: Programming Language :: Python
Classifier: Programming Language :: Python :: 3
Classifier: Programming Language :: Python :: 3.7
Classifier: License :: OSI Approved :: Apache Software License
Classifier: Operating System :: OS Independent
Classifier: Natural Language :: English
Classifier: Intended Audience :: Developers
Requires-Python: ==3.7.*
Requires-Dist: pandas (==1.0.0)
Requires-Dist: requests (==2.22.0)
Requires-Dist: xlrd (==1.2.0)
